podcast_dl/__init__.py
podcast_dl/cli.py
podcast_dl/podcast_dl.py
podcast_dl/podcasts.py
podcast_dl/rss_parsers.py
podcast_dl/site_parser.py
simple_podcast_dl-1.7.dist-info/METADATA
simple_podcast_dl-1.7.dist-info/WHEEL
simple_podcast_dl-1.7.dist-info/LICENSE
simple_podcast_dl-1.7.dist-info/entry_points.txt
simple_podcast_dl-1.7.dist-info/RECORD
