Metadata-Version: 2.1
Name: simple-podcast-dl
Version: 1.7
Summary: Simple podcast downloader (podcatcher)
Home-page: https://github.com/kissgyorgy/simple-podcast-dl
License: MIT
Keywords: podcasts
Author: Kiss György
Author-email: kissgyorgy@me.com
Requires-Python: >=3.6
Classifier: License :: OSI Approved :: MIT License
Classifier: Programming Language :: Python
Classifier: Programming Language :: Python :: 3
Classifier: Programming Language :: Python :: 3.6
Classifier: Programming Language :: Python :: 3.7
Classifier: Programming Language :: Python :: 3.8
Classifier: Programming Language :: Python :: 3.9
Classifier: Programming Language :: Python :: 3.10
Classifier: Programming Language :: Python :: 3.11
Classifier: Programming Language :: Python :: 3
Requires-Dist: aiodns (>=1.1,<2.0)
Requires-Dist: attrs (>=18.2,<19.0)
Requires-Dist: click (>=7.0,<8.0)
Requires-Dist: httpx (>=0.18.2,<0.19.0)
Requires-Dist: lxml (>=4.2,<5.0)
Requires-Dist: python-slugify (>=1.2,<2.0)
Project-URL: Repository, https://github.com/kissgyorgy/simple-podcast-dl
